README.md
setup.py
Optimizer/__init__.py
Optimizer/optimizer.py
SkvalpOpt.egg-info/PKG-INFO
SkvalpOpt.egg-info/SOURCES.txt
SkvalpOpt.egg-info/dependency_links.txt
SkvalpOpt.egg-info/top_level.txt