Metadata-Version: 2.1
Name: SkvalpOpt
Version: 1.0
Summary: Skvalp Hackathon Optimizer
Home-page: https://github.com/vishnuav08/SkvalpOptimizerPackage`
Author: Skvalp
Author-email: vishnu.powergrid@email.com
